yacargo/__init__.py
yacargo/exceptions.py
yacargo/objects.py
yacargo-0.0.6.dist-info/METADATA
yacargo-0.0.6.dist-info/WHEEL
yacargo-0.0.6.dist-info/top_level.txt
yacargo-0.0.6.dist-info/RECORD
