Metadata-Version: 2.1
Name: yacargo
Version: 0.0.6
Summary: Yandex.Taxi Cargo API SDK
Home-page: https://github.com/yegorov-p/yacargo
Author: Pasha Yegorov
Author-email: yegorov.p@gmail.com
License: UNKNOWN
Keywords: yandex taxi cargo
Platform: UNKNOWN
Classifier: Development Status :: 4 - Beta
Classifier: Programming Language :: Python
Classifier: Topic :: Software Development :: Libraries
Requires-Dist: requests
Requires-Dist: typeguard
Requires-Dist: pyyaml
